calculator/__init__.py
calculator/calculator.py
escalculator-1.1.0.dist-info/LICENSE
escalculator-1.1.0.dist-info/METADATA
escalculator-1.1.0.dist-info/WHEEL
escalculator-1.1.0.dist-info/top_level.txt
escalculator-1.1.0.dist-info/RECORD
