Metadata-Version: 2.1
Name: escalculator
Version: 1.1.0
Summary: calculator with basic operations
Home-page: UNKNOWN
Author: Edvard
Author-email: edvardas.ux@gmail.com
License: MIT
Platform: UNKNOWN
